teste_bem_vindo/__init__.py
teste_bem_vindo/file1_name.py
teste_bem_vindo-0.0.1.dist-info/METADATA
teste_bem_vindo-0.0.1.dist-info/WHEEL
teste_bem_vindo-0.0.1.dist-info/top_level.txt
teste_bem_vindo-0.0.1.dist-info/RECORD
