Metadata-Version: 2.4
Name: teste_bem_vindo
Version: 0.0.1
Summary: Desafio Dio criando um pacote
Home-page: https://github.com/FelipeRobertoB/simple-package-template
Author: Felipe
Author-email: feliperobertoblanco@gmail.com
Requires-Python: >=3.8
Dynamic: author
Dynamic: author-email
Dynamic: description
Dynamic: description-content-type
Dynamic: home-page
Dynamic: requires-python
Dynamic: summary
